better_apidoc.py
better_apidoc-0.2.0.dist-info/DESCRIPTION.rst
better_apidoc-0.2.0.dist-info/METADATA
better_apidoc-0.2.0.dist-info/RECORD
better_apidoc-0.2.0.dist-info/WHEEL
better_apidoc-0.2.0.dist-info/entry_points.txt
better_apidoc-0.2.0.dist-info/metadata.json
better_apidoc-0.2.0.dist-info/top_level.txt
