Metadata-Version: 2.0
Name: better-apidoc
Version: 0.2.0
Summary: A version of sphinx-apidoc with support for templating
Home-page: https://github.com/goerz/better-apidoc
Author: Michael Goerz
Author-email: mail@michaelgoerz.net
License: UNKNOWN
Platform: UNKNOWN
Classifier: Environment :: Console
Classifier: Natural Language :: English
Classifier: License :: OSI Approved :: BSD License
Classifier: Programming Language :: Python
Classifier: Programming Language :: Python :: 2
Classifier: Programming Language :: Python :: 2.7
Classifier: Programming Language :: Python :: 3
Classifier: Programming Language :: Python :: 3.3
Classifier: Programming Language :: Python :: 3.4
Provides-Extra: dev
Requires-Dist: sphinx
Requires-Dist: jinja2
Provides-Extra: dev
Requires-Dist: pytest; extra == 'dev'
